{"@context":"https://schema.org","@type":"CreativeWork","@id":"https://jr.mitou.org/projects/2021/web_koten.json","name":"Web個展 - Webであることを活かしたオンライン展示形式の模索","description":"2019年終わりごろから流行し始めたCOVID-19によって、いくつもの現実の個展の開催が中止、延期され、開催する場合も大きな制限を受けることとなりました。それを受け、最近ではWebサイト上で閲覧できる展示も増えましたが、その多くは「現実の個展を再現する」ことに主眼をおいたものであり、あくまでCOVID-19の流行による現実の個展の代替的なものという意味合いが大きいものでした。Web個展ではWebという媒体の特性をより引き出すことに焦点を当て、観覧者がワクワクできるような個展を目指します。","creator":[{"@type":"Person","name":"椎名"}],"contributor":{"@type":"Person","name":"関 喜史","url":"https://jr.mitou.org/mentors/#yoshifumi_seki"},"video":{"@type":"VideoObject","name":"Web個展 - Webであることを活かしたオンライン展示形式の模索","embedUrl":"https://www.youtube.com/embed/GT4WIiHOyeg","description":"2019年終わりごろから流行し始めたCOVID-19によって、いくつもの現実の個展の開催が中止、延期され、開催する場合も大きな制限を受けることとなりました。それを受け、最近ではWebサイト上で閲覧できる展示も増えましたが、その多くは「現実の個展を再現する」ことに主眼をおいたものであり、あくまでCOVID-19の流行による現実の個展の代替的なものという意味合いが大きいものでした。Web個展ではWebという媒体の特性をより引き出すことに焦点を当て、観覧者がワクワクできるような個展を目指します。","thumbnailUrl":"/assets/img/projects/2021/web-koten.webp","uploadDate":"2021-11-03T10:00:00+09:00"},"dateCreated":"2021-10-01T10:00:00+09:00","educationalLevel":"小中高生・高専生","inLanguage":"ja","isPartOf":{"@type":"EducationalProgram","name":"未踏ジュニア","url":"https://jr.mitou.org"}}